odoo8_addon_business_requirement_deliverable-8.0.5.0.1-py2.7-nspkg.pth
odoo8_addon_business_requirement_deliverable-8.0.5.0.1.dist-info/DESCRIPTION.rst
odoo8_addon_business_requirement_deliverable-8.0.5.0.1.dist-info/METADATA
odoo8_addon_business_requirement_deliverable-8.0.5.0.1.dist-info/RECORD
odoo8_addon_business_requirement_deliverable-8.0.5.0.1.dist-info/WHEEL
odoo8_addon_business_requirement_deliverable-8.0.5.0.1.dist-info/metadata.json
odoo8_addon_business_requirement_deliverable-8.0.5.0.1.dist-info/namespace_packages.txt
odoo8_addon_business_requirement_deliverable-8.0.5.0.1.dist-info/top_level.txt
odoo_addons/business_requirement_deliverable/README.rst
odoo_addons/business_requirement_deliverable/__init__.py
odoo_addons/business_requirement_deliverable/__openerp__.py
odoo_addons/business_requirement_deliverable/i18n/sl.po
odoo_addons/business_requirement_deliverable/models/__init__.py
odoo_addons/business_requirement_deliverable/models/business.py
odoo_addons/business_requirement_deliverable/models/res_partner.py
odoo_addons/business_requirement_deliverable/report/__init__.py
odoo_addons/business_requirement_deliverable/report/br_deliverable_report.py
odoo_addons/business_requirement_deliverable/report/br_deliverable_report_view.xml
odoo_addons/business_requirement_deliverable/report/br_deliverable_sale_report.py
odoo_addons/business_requirement_deliverable/report/br_deliverable_sale_report_view.xml
odoo_addons/business_requirement_deliverable/security/business_requirement_deliverable_security.xml
odoo_addons/business_requirement_deliverable/security/ir.model.access.csv
odoo_addons/business_requirement_deliverable/static/description/icon.png
odoo_addons/business_requirement_deliverable/static/img/bus_req_deliverable.png
odoo_addons/business_requirement_deliverable/static/img/bus_req_deliverable2.png
odoo_addons/business_requirement_deliverable/static/img/bus_req_resource.png
odoo_addons/business_requirement_deliverable/tests/__init__.py
odoo_addons/business_requirement_deliverable/tests/test_br.py
odoo_addons/business_requirement_deliverable/views/business_view.xml
odoo_addons/business_requirement_deliverable/views/res_partner.xml
